lenvert/__init__.py
lenvert/utils.py
lenvert/length/__init__.py
lenvert/length/api.py
lenvert/length/core.py
lenvert/weight/__init__.py
lenvert/weight/api.py
lenvert/weight/core.py
lenvert_python-0.1.0.dist-info/LICENSE
lenvert_python-0.1.0.dist-info/METADATA
lenvert_python-0.1.0.dist-info/WHEEL
lenvert_python-0.1.0.dist-info/top_level.txt
lenvert_python-0.1.0.dist-info/RECORD
