Metadata-Version: 2.1
Name: lenvert_python
Version: 0.1.0
Summary: A package for converting imperial lengths and weights
Home-page: https://github.com/elias-dzobo/lenvert
Author: Elias Dzobo
License-File: LICENSE
Requires-Dist: numpy >=1.10
Requires-Dist: pandas
